pyqtmd/__init__.py
pyqtmd/__main__.py
pyqtmd/helpers.py
pyqtmd/screen.py
pyqtmd/designer/article.ui
pyqtmd/images/NotFound.png
pyqtmd-0.1.1.dist-info/LICENSE.txt
pyqtmd-0.1.1.dist-info/METADATA
pyqtmd-0.1.1.dist-info/WHEEL
pyqtmd-0.1.1.dist-info/entry_points.txt
pyqtmd-0.1.1.dist-info/top_level.txt
pyqtmd-0.1.1.dist-info/RECORD
