Metadata-Version: 2.1
Name: pyqtmd
Version: 0.1.1
Summary: A qt markdown viewer because why doesn't a good gui md viewer exist already ffs
Home-page: https://git.tristans.cloud/tristan/pyqtmd
Author: MyBeansAreBaked
Author-email: tristan@tristans.cloud
License: GPLv3+
Platform: UNKNOWN
Classifier: Programming Language :: Python :: 3
Classifier: License :: OSI Approved :: GNU General Public License v3 or later (GPLv3+)
Classifier: Operating System :: OS Independent
Requires-Python: >=3.7
License-File: LICENSE.txt
Requires-Dist: pyqt5
Requires-Dist: requests
